geojsonboundingbox/__init__.py
geojsonboundingbox/__main__.py
geojsonboundingbox-0.1.4.dist-info/WHEEL
geojsonboundingbox-0.1.4.dist-info/METADATA
geojsonboundingbox-0.1.4.dist-info/RECORD
