Metadata-Version: 2.1
Name: geojsonboundingbox
Version: 0.1.4
Summary: Prints out the bounding box of a geojson input file
Home-page: https://github.com/ericmccowan/geojsonboundingbox
License: MIT
Author: Eric McCowan
Author-email: eric.mccowan@servian.com
Requires-Python: >=3.0,<4.0
Classifier: License :: OSI Approved :: MIT License
Classifier: Programming Language :: Python :: 3
Project-URL: Repository, https://github.com/ericmccowan/geojsonboundingbox
